beancount_daoru/__init__.py
beancount_daoru/hook.py
beancount_daoru/importer.py
beancount_daoru/py.typed
beancount_daoru/reader.py
beancount_daoru/utils.py
beancount_daoru/hooks/__init__.py
beancount_daoru/hooks/path_to_name.py
beancount_daoru/hooks/predict_missing_posting.py
beancount_daoru/hooks/reorder_by_importer_name.py
beancount_daoru/importers/__init__.py
beancount_daoru/importers/alipay.py
beancount_daoru/importers/boc.py
beancount_daoru/importers/bocom.py
beancount_daoru/importers/jd.py
beancount_daoru/importers/meituan.py
beancount_daoru/importers/wechat.py
beancount_daoru/readers/__init__.py
beancount_daoru/readers/excel.py
beancount_daoru/readers/pdf_table.py
beancount_daoru-0.1.0.dist-info/METADATA
beancount_daoru-0.1.0.dist-info/WHEEL
beancount_daoru-0.1.0.dist-info/licenses/LICENSE.txt
beancount_daoru-0.1.0.dist-info/RECORD
