Metadata-Version: 2.4
Name: beancount-daoru
Version: 0.1.0
Summary: beancount importers for Chinese
Project-URL: repository, https://github.com/aqni/beancount-daoru
Author-email: AN Qi <aqnin@outlook.com>
License-Expression: MIT
License-File: LICENSE.txt
Requires-Python: >=3.10
Requires-Dist: beangulp<0.3,>=0.2
Requires-Dist: pdfplumber>=0.11.8
Requires-Dist: pydantic>=2.12
Requires-Dist: pyexcel-xlsxr>=0.6.2
Requires-Dist: pyexcel>=0.7
Requires-Dist: typing-extensions>=4.15.0
Provides-Extra: llm
Requires-Dist: diskcache>=5.6.3; extra == 'llm'
Requires-Dist: openai>=2.11.0; extra == 'llm'
Requires-Dist: usearch>=2.21.0; extra == 'llm'
